[
  {
    "id": "20260413-CNY",
    "countryCode": "CN",
    "currencyName": "중국 위안",
    "currencyCode": "CNY",
    "rate": 218.1,
    "date": "2026-04-13",
    "type": "bank",
    "cashBuy": 229,
    "cashSell": 207.2,
    "ttSend": 220.28,
    "ttReceive": 215.92,
    "timestamp": "2026-04-13T12:08:08.583Z"
  },
  {
    "id": "20260413-EUR",
    "countryCode": "EU",
    "currencyName": "유로",
    "currencyCode": "EUR",
    "rate": 1741.23,
    "date": "2026-04-13",
    "type": "bank",
    "cashBuy": 1775.88,
    "cashSell": 1706.58,
    "ttSend": 1758.64,
    "ttReceive": 1723.82,
    "timestamp": "2026-04-13T12:08:08.384Z"
  },
  {
    "id": "20260413-GBP",
    "countryCode": "GB",
    "currencyName": "영국 파운드",
    "currencyCode": "GBP",
    "rate": 1999.67,
    "date": "2026-04-13",
    "type": "bank",
    "cashBuy": 2039.06,
    "cashSell": 1960.28,
    "ttSend": 2019.66,
    "ttReceive": 1979.68,
    "timestamp": "2026-04-13T12:08:08.978Z"
  },
  {
    "id": "20260413-JPY",
    "countryCode": "JP",
    "currencyName": "일본 엔",
    "currencyCode": "JPY",
    "rate": 932.4,
    "date": "2026-04-13",
    "type": "bank",
    "cashBuy": 948.71,
    "cashSell": 916.09,
    "ttSend": 941.53,
    "ttReceive": 923.27,
    "timestamp": "2026-04-13T12:08:08.781Z"
  },
  {
    "id": "20260413-USD",
    "countryCode": "US",
    "currencyName": "미국 달러",
    "currencyCode": "USD",
    "rate": 1490.4,
    "date": "2026-04-13",
    "type": "bank",
    "cashBuy": 1516.48,
    "cashSell": 1464.32,
    "ttSend": 1505,
    "ttReceive": 1475.8,
    "timestamp": "2026-04-13T12:08:08.182Z"
  }
]