[
  {
    "id": "20260508-CNY",
    "countryCode": "CN",
    "currencyName": "중국 위안",
    "currencyCode": "CNY",
    "rate": 215.39,
    "date": "2026-05-08",
    "type": "bank",
    "cashBuy": 226.15,
    "cashSell": 204.63,
    "ttSend": 217.54,
    "ttReceive": 213.24,
    "timestamp": "2026-05-08T02:43:19.318Z"
  },
  {
    "id": "20260508-EUR",
    "countryCode": "EU",
    "currencyName": "유로",
    "currencyCode": "EUR",
    "rate": 1718.42,
    "date": "2026-05-08",
    "type": "bank",
    "cashBuy": 1752.61,
    "cashSell": 1684.23,
    "ttSend": 1735.6,
    "ttReceive": 1701.24,
    "timestamp": "2026-05-08T02:43:19.135Z"
  },
  {
    "id": "20260508-GBP",
    "countryCode": "GB",
    "currencyName": "영국 파운드",
    "currencyCode": "GBP",
    "rate": 1986.18,
    "date": "2026-05-08",
    "type": "bank",
    "cashBuy": 2025.3,
    "cashSell": 1947.06,
    "ttSend": 2006.04,
    "ttReceive": 1966.32,
    "timestamp": "2026-05-08T02:43:19.684Z"
  },
  {
    "id": "20260508-JPY",
    "countryCode": "JP",
    "currencyName": "일본 엔",
    "currencyCode": "JPY",
    "rate": 933.86,
    "date": "2026-05-08",
    "type": "bank",
    "cashBuy": 950.2,
    "cashSell": 917.52,
    "ttSend": 943.01,
    "ttReceive": 924.71,
    "timestamp": "2026-05-08T02:43:19.502Z"
  },
  {
    "id": "20260508-USD",
    "countryCode": "US",
    "currencyName": "미국 달러",
    "currencyCode": "USD",
    "rate": 1465.6,
    "date": "2026-05-08",
    "type": "bank",
    "cashBuy": 1491.24,
    "cashSell": 1439.96,
    "ttSend": 1479.9,
    "ttReceive": 1451.3,
    "timestamp": "2026-05-08T02:43:18.945Z"
  }
]