[
  {
    "id": "20260317-CNY",
    "countryCode": "CN",
    "currencyName": "중국 위안",
    "currencyCode": "CNY",
    "rate": 216.32,
    "date": "2026-03-17",
    "type": "bank",
    "cashBuy": 227.13,
    "cashSell": 205.51,
    "ttSend": 218.48,
    "ttReceive": 214.16,
    "timestamp": "2026-03-17T05:40:56.638Z"
  },
  {
    "id": "20260317-EUR",
    "countryCode": "EU",
    "currencyName": "유로",
    "currencyCode": "EUR",
    "rate": 1712.23,
    "date": "2026-03-17",
    "type": "bank",
    "cashBuy": 1746.3,
    "cashSell": 1678.16,
    "ttSend": 1729.35,
    "ttReceive": 1695.11,
    "timestamp": "2026-03-17T05:40:56.488Z"
  },
  {
    "id": "20260317-GBP",
    "countryCode": "GB",
    "currencyName": "영국 파운드",
    "currencyCode": "GBP",
    "rate": 1982.4,
    "date": "2026-03-17",
    "type": "bank",
    "cashBuy": 2021.45,
    "cashSell": 1943.35,
    "ttSend": 2002.22,
    "ttReceive": 1962.58,
    "timestamp": "2026-03-17T05:40:56.938Z"
  },
  {
    "id": "20260317-JPY",
    "countryCode": "JP",
    "currencyName": "일본 엔",
    "currencyCode": "JPY",
    "rate": 935.07,
    "date": "2026-03-17",
    "type": "bank",
    "cashBuy": 951.43,
    "cashSell": 918.71,
    "ttSend": 944.23,
    "ttReceive": 925.91,
    "timestamp": "2026-03-17T05:40:56.789Z"
  },
  {
    "id": "20260317-USD",
    "countryCode": "US",
    "currencyName": "미국 달러",
    "currencyCode": "USD",
    "rate": 1489.8,
    "date": "2026-03-17",
    "type": "bank",
    "cashBuy": 1515.87,
    "cashSell": 1463.73,
    "ttSend": 1504.4,
    "ttReceive": 1475.2,
    "timestamp": "2026-03-17T05:40:56.113Z"
  }
]