[
  {
    "id": "20260706-CNY",
    "countryCode": "CN",
    "currencyName": "중국 위안",
    "currencyCode": "CNY",
    "rate": 225.36,
    "date": "2026-07-06",
    "type": "bank",
    "cashBuy": 236.62,
    "cashSell": 214.1,
    "ttSend": 227.61,
    "ttReceive": 223.11,
    "timestamp": "2026-07-06T10:12:43.585Z"
  },
  {
    "id": "20260706-EUR",
    "countryCode": "EU",
    "currencyName": "유로",
    "currencyCode": "EUR",
    "rate": 1748.4,
    "date": "2026-07-06",
    "type": "bank",
    "cashBuy": 1783.19,
    "cashSell": 1713.61,
    "ttSend": 1765.88,
    "ttReceive": 1730.92,
    "timestamp": "2026-07-06T10:12:43.423Z"
  },
  {
    "id": "20260706-GBP",
    "countryCode": "GB",
    "currencyName": "영국 파운드",
    "currencyCode": "GBP",
    "rate": 2043.15,
    "date": "2026-07-06",
    "type": "bank",
    "cashBuy": 2083.4,
    "cashSell": 2002.9,
    "ttSend": 2063.58,
    "ttReceive": 2022.72,
    "timestamp": "2026-07-06T10:12:43.912Z"
  },
  {
    "id": "20260706-JPY",
    "countryCode": "JP",
    "currencyName": "일본 엔",
    "currencyCode": "JPY",
    "rate": 943.64,
    "date": "2026-07-06",
    "type": "bank",
    "cashBuy": 960.15,
    "cashSell": 927.13,
    "ttSend": 952.88,
    "ttReceive": 934.4,
    "timestamp": "2026-07-06T10:12:43.750Z"
  },
  {
    "id": "20260706-USD",
    "countryCode": "US",
    "currencyName": "미국 달러",
    "currencyCode": "USD",
    "rate": 1532,
    "date": "2026-07-06",
    "type": "bank",
    "cashBuy": 1558.81,
    "cashSell": 1505.19,
    "ttSend": 1547,
    "ttReceive": 1517,
    "timestamp": "2026-07-06T10:12:43.255Z"
  }
]