[
  {
    "id": "20260408-CNY",
    "countryCode": "CN",
    "currencyName": "중국 위안",
    "currencyCode": "CNY",
    "rate": 216.2,
    "date": "2026-04-08",
    "type": "bank",
    "cashBuy": 227.01,
    "cashSell": 205.39,
    "ttSend": 218.36,
    "ttReceive": 214.04,
    "timestamp": "2026-04-08T03:38:23.468Z"
  },
  {
    "id": "20260408-EUR",
    "countryCode": "EU",
    "currencyName": "유로",
    "currencyCode": "EUR",
    "rate": 1723.83,
    "date": "2026-04-08",
    "type": "bank",
    "cashBuy": 1758.13,
    "cashSell": 1689.53,
    "ttSend": 1741.06,
    "ttReceive": 1706.6,
    "timestamp": "2026-04-08T03:38:23.316Z"
  },
  {
    "id": "20260408-GBP",
    "countryCode": "GB",
    "currencyName": "영국 파운드",
    "currencyCode": "GBP",
    "rate": 1978.53,
    "date": "2026-04-08",
    "type": "bank",
    "cashBuy": 2017.5,
    "cashSell": 1939.56,
    "ttSend": 1998.31,
    "ttReceive": 1958.75,
    "timestamp": "2026-04-08T03:38:23.773Z"
  },
  {
    "id": "20260408-JPY",
    "countryCode": "JP",
    "currencyName": "일본 엔",
    "currencyCode": "JPY",
    "rate": 932.41,
    "date": "2026-04-08",
    "type": "bank",
    "cashBuy": 948.72,
    "cashSell": 916.1,
    "ttSend": 941.54,
    "ttReceive": 923.28,
    "timestamp": "2026-04-08T03:38:23.622Z"
  },
  {
    "id": "20260408-USD",
    "countryCode": "US",
    "currencyName": "미국 달러",
    "currencyCode": "USD",
    "rate": 1477.4,
    "date": "2026-04-08",
    "type": "bank",
    "cashBuy": 1503.25,
    "cashSell": 1451.55,
    "ttSend": 1491.8,
    "ttReceive": 1463,
    "timestamp": "2026-04-08T03:38:23.158Z"
  }
]