[
  {
    "id": "20260625-CNY",
    "countryCode": "CN",
    "currencyName": "중국 위안",
    "currencyCode": "CNY",
    "rate": 226.79,
    "date": "2026-06-25",
    "type": "bank",
    "cashBuy": 238.12,
    "cashSell": 215.46,
    "ttSend": 229.05,
    "ttReceive": 224.53,
    "timestamp": "2026-06-25T11:13:45.739Z"
  },
  {
    "id": "20260625-EUR",
    "countryCode": "EU",
    "currencyName": "유로",
    "currencyCode": "EUR",
    "rate": 1750.57,
    "date": "2026-06-25",
    "type": "bank",
    "cashBuy": 1785.4,
    "cashSell": 1715.74,
    "ttSend": 1768.07,
    "ttReceive": 1733.07,
    "timestamp": "2026-06-25T11:13:45.535Z"
  },
  {
    "id": "20260625-GBP",
    "countryCode": "GB",
    "currencyName": "영국 파운드",
    "currencyCode": "GBP",
    "rate": 2031.72,
    "date": "2026-06-25",
    "type": "bank",
    "cashBuy": 2071.74,
    "cashSell": 1991.7,
    "ttSend": 2052.03,
    "ttReceive": 2011.41,
    "timestamp": "2026-06-25T11:13:46.149Z"
  },
  {
    "id": "20260625-JPY",
    "countryCode": "JP",
    "currencyName": "일본 엔",
    "currencyCode": "JPY",
    "rate": 953.27,
    "date": "2026-06-25",
    "type": "bank",
    "cashBuy": 969.95,
    "cashSell": 936.59,
    "ttSend": 962.61,
    "ttReceive": 943.93,
    "timestamp": "2026-06-25T11:13:45.944Z"
  },
  {
    "id": "20260625-USD",
    "countryCode": "US",
    "currencyName": "미국 달러",
    "currencyCode": "USD",
    "rate": 1543.1,
    "date": "2026-06-25",
    "type": "bank",
    "cashBuy": 1570.1,
    "cashSell": 1516.1,
    "ttSend": 1558.2,
    "ttReceive": 1528,
    "timestamp": "2026-06-25T11:13:45.323Z"
  }
]